mcp_djh/__init__.py
mcp_djh-0.1.3.dist-info/METADATA
mcp_djh-0.1.3.dist-info/WHEEL
mcp_djh-0.1.3.dist-info/entry_points.txt
mcp_djh-0.1.3.dist-info/RECORD
