Metadata-Version: 2.4
Name: mcp-djh
Version: 0.1.3
Summary: Add your description here
Author: dartou
Requires-Python: >=3.11
Requires-Dist: mcp[cli]>=1.9.4
Requires-Dist: requests
